tap_airbyte/__init__.py
tap_airbyte/tap.py
tap_airbyte/tests/__init__.py
tap_airbyte/tests/fixtures/KPHX.csv
tap_airbyte/tests/fixtures/KPHX.singer
tap_airbyte/tests/fixtures/PUBLIC_APIS.singer
tap_airbyte/tests/fixtures/SMEARGLE.singer
tap_airbyte/tests/test_core.py
tap_airbyte/tests/test_syncs.py
tap_airbyte-0.0.2.dist-info/LICENSE
tap_airbyte-0.0.2.dist-info/METADATA
tap_airbyte-0.0.2.dist-info/WHEEL
tap_airbyte-0.0.2.dist-info/entry_points.txt
tap_airbyte-0.0.2.dist-info/RECORD
